uada80/__init__.py
uada80/ast_nodes.py
uada80/compiler.py
uada80/ir.py
uada80/lexer.py
uada80/lowering.py
uada80/main.py
uada80/parser.py
uada80/runtime_manager.py
uada80/semantic.py
uada80/symbol_table.py
uada80/type_system.py
uada80/codegen/__init__.py
uada80/optimizer/__init__.py
uada80/optimizer/ast_optimizer.py
uada80/optimizer/config.py
uada80-0.3.0.dist-info/METADATA
uada80-0.3.0.dist-info/WHEEL
uada80-0.3.0.dist-info/entry_points.txt
uada80-0.3.0.dist-info/top_level.txt
uada80-0.3.0.dist-info/RECORD
