Metadata-Version: 2.4
Name: uada80
Version: 0.3.0
Summary: Ada compiler targeting Z80 processor
Author: uada80 project
License: GPLv2
Project-URL: Homepage, https://github.com/avwohl/uada80
Project-URL: Repository, https://github.com/avwohl/uada80
Keywords: ada,compiler,z80,retro,embedded
Classifier: Development Status :: 2 - Pre-Alpha
Classifier: Intended Audience :: Developers
Classifier: License :: OSI Approved :: GNU General Public License v2 (GPLv2)
Classifier: Programming Language :: Python :: 3
Classifier: Programming Language :: Python :: 3.10
Classifier: Programming Language :: Python :: 3.11
Classifier: Programming Language :: Python :: 3.12
Classifier: Topic :: Software Development :: Compilers
Requires-Python: >=3.10
Requires-Dist: upeepz80>=0.1.0
Provides-Extra: dev
Requires-Dist: pytest>=7.4.0; extra == "dev"
Requires-Dist: pytest-cov>=4.1.0; extra == "dev"
Requires-Dist: mypy>=1.5.0; extra == "dev"
Requires-Dist: black>=23.7.0; extra == "dev"
Requires-Dist: ruff>=0.0.285; extra == "dev"
Requires-Dist: pylint>=3.0.0; extra == "dev"
